Src/alu.sv
module ALU(
    input logic [31:0] a,
    input logic [31:0] b,
    input logic [3:0] sel,

    output logic [31:0] out,
    output logic zero
);

    logic [4:0] shift;
    assign shift = b[4:0];

    always_comb begin
        case(sel)

            4'd00: out = a+b;                           //add
            4'd01: out = a-b;                           //sub
            4'd02: out = a&b;                           //and
            4'd03: out = a|b;                           //or
            4'd04: out = a^b;                           //xor
            4'd05: out = a << shift;                    //shift left
            4'd06: out = a >> shift;                    //shift right
            4'd07: out = $signed(a) >>> shift;          //shift right signed
            4'd08: out = $signed(a) < $signed(b);       //compare signed
            4'd09: out = a < b;                         //compare

            default: out = 32'h0;

            
        endcase

        if(out == 32'h0)
            zero = 1;
        else
            zero = 0;
            
    end




endmodule

Src/alu_tb.sv
module alu_tb;

    logic [31:0] a;
    logic [31:0] b;
    logic [3:0] sel;

    logic [31:0] out;
    logic zero;

    ALU ArithmaticLU(
            .a(a), 
            .b(b), 
            .sel(sel), 
            .out(out),
            .zero(zero)
            );

    
    initial begin


        $dumpfile("alu.vcd");
        $dumpvars(0, alu_tb);

        //Testing all cases:

        //Test 1: Addition
        a = 32'd4;
        b = 32'd9;
        sel = 4'd0;
        #1;

        if (out == a+b && zero == 0) begin
            $display("Success: out = %d", out);
        end
        else begin
            $display("Fail: out = %d, should be %d", out, a+b);
        end

        //Test 2: Subtraction
        sel = 4'd1;
        #1;

        if (out == a-b && zero == 0) begin
            $display("Success: out = %d", out);
        end
        else begin
            $display("Fail: out = %d, should be %d", out, a-b);
        end

        //Test 3: AND
        sel = 4'd2;
        #1;

        if (out == (a&b) && zero == 1) begin
            $display("Success: out = %d", out);
        end
        else begin
            $display("Fail: out = %d, should be %d", out, a&b);
        end
        
        //Test 4: OR
        sel = 4'd3;
        #1;

        if (out == a|b && zero == 0) begin
            $display("Success: out = %d", out);
        end
        else begin
            $display("Fail: out = %d, should be %d", out, a|b);
        end

        //Test 5: XOR
        sel = 4'd4;
        #1;

        if (out == a^b && zero == 0) begin
            $display("Success: out = %d", out);
        end
        else begin
            $display("Fail: out = %d, should be %d", out, a^b);
        end

        //Test 6: shift left
        sel = 4'd5;
        #1;

        if (out == a<<b[4:0] && zero == 0) begin
            $display("Success: out = %d", out);
        end
        else begin
            $display("Fail: out = %d, should be %d", out, a<<b[4:0]);
        end

        //Test 7: shift right
        sel = 4'd6;
        a = 32'd5;
        b = 32'd2;
        #1;

        if (out == a>>b[4:0] && zero == 0) begin
            $display("Success: out = %d", out);
        end
        else begin
            $display("Fail: out = %d, should be %d", out, a>>b[4:0]);
        end

        //Test 8: shift right (signed)
        sel = 4'd7;
        a = -32'd5;
        #1;

        if ($signed(out) == ($signed(a) >>> b[4:0]) && zero == 0) begin
            $display("Success: out = %d", out);
        end
        else begin
            $display("Fail: out = %d, should be %d", out,  $signed(a) >>> b[4:0]);
        end

        //Test 9: signed compare
        sel = 4'd8;
        #1;

        if (out == {31'b0, ($signed(a) < $signed(b))} && zero == 0) begin
            $display("Success: out = %d", out);
        end
        else begin
            $display("Fail: out = %d, should be %d", out,  $signed(a) < $signed(b));
        end

        // Test 10: compare
        sel = 4'd9;
        a = 32'd5;
        #1;

        if (out == a<b && zero == 1) begin
            $display("Success: out = %d", out);
        end
        else begin
            $display("Fail: out = %d, should be %d", out, a<b);
        end

        //Test 11: zero
        sel = 4'd1;
        a = 32'd1;
        b = 32'd1;
        #1;

        if (out == a-b && zero == 1) begin
            $display("Success: out = %d", out);
        end
        else begin
            $display("Fail: out = %d, should be %d", out,  a-b);
        end
        
        
        $finish;       


    end

endmodule

Src/alu.vcd
$date
	Sat May 16 22:18:29 2026
$end
$version
	Icarus Verilog
$end
$timescale
	1s
$end
$scope module alu_tb $end
$var wire 1 ! zero $end
$var wire 32 " out [31:0] $end
$var reg 32 # a [31:0] $end
$var reg 32 $ b [31:0] $end
$var reg 4 % sel [3:0] $end
$scope module ArithmaticLU $end
$var wire 32 & a [31:0] $end
$var wire 32 ' b [31:0] $end
$var wire 4 ( sel [3:0] $end
$var wire 5 ) shift [4:0] $end
$var reg 32 * out [31:0] $end
$var reg 1 ! zero $end
$upscope $end
$upscope $end
$enddefinitions $end
$comment Show the parameter values. $end
$dumpall
$end
#0
$dumpvars
b1101 *
b1001 )
b0 (
b1001 '
b100 &
b0 %
b1001 $
b100 #
b1101 "
0!
$end
#1
b11111111111111111111111111111011 "
b11111111111111111111111111111011 *
b1 %
b1 (
#2
1!
b0 "
b0 *
b10 %
b10 (
#3
0!
b1101 "
b1101 *
b11 %
b11 (
#4
b100 %
b100 (
#5
b100000000000 "
b100000000000 *
b101 %
b101 (
#6
b10 )
0!
b1 "
b1 *
b10 $
b10 '
b101 #
b101 &
b110 %
b110 (
#7
b11111111111111111111111111111110 "
b11111111111111111111111111111110 *
b11111111111111111111111111111011 #
b11111111111111111111111111111011 &
b111 %
b111 (
#8
b1 "
b1 *
b1000 %
b1000 (
#9
1!
b0 "
b0 *
b101 #
b101 &
b1001 %
b1001 (
#10
b1 )
b1 $
b1 '
b1 #
b1 &
b1 %
b1 (
