Src/controlUnit.sv
module ControlUnit(
    input logic [31:0] inst,
    
    output logic [2:0] ImmSel,
    output logic RegWrite,
    output logic ALUSrc,
    output logic [1:0] ALUop,
    output logic MemRead,
    output logic MemWrite,
    output logic MemtoReg,
    output logic Branch,
    output logic [2:0] funct3,
    output logic       funct7_bit6
);

    logic [6:0] opcode;

    assign opcode = inst[6:0];
    assign funct3 = inst[14:12];
    assign funct7_bit6 = inst[30];


    always @(*) begin
        
        case (opcode)
            7'h33: begin // R type
                ImmSel      = 3'd0; 
                RegWrite    = 1'd1;
                ALUSrc      = 1'd0;
                ALUop       = 2'd2;
                MemRead     = 1'd0;
                MemWrite    = 1'd0;
                MemtoReg    = 1'd0;
                Branch      = 1'd0;

            end
            7'h13, 7'h03, 7'h67: begin //I Type
                ImmSel      = 3'd1; 
                RegWrite    = 1'd1;
                ALUSrc      = 1'd1;
                MemWrite    = 1'd0;
                Branch      = 1'd0;

                if(opcode == 7'h03) begin
                    MemRead  = 1'd1;
                    MemtoReg = 1'd1;
                    ALUop    = 2'd0;
                end else if(opcode == 7'h67) begin
                    MemRead  = 1'd0;
                    MemtoReg = 1'dx;
                    ALUop    = 2'd0;
                end else begin
                    MemRead  = 1'd0;
                    MemtoReg = 1'd0; 
                    ALUop    = 2'd3;       
                end
                
                
            end

            7'h23: begin //S Type
                ImmSel      = 3'd2; 
                RegWrite    = 1'd0;
                ALUSrc      = 1'd1;
                ALUop       = 2'd00;
                MemRead     = 1'd0;
                MemWrite    = 1'd1;
                MemtoReg    = 1'dx;
                Branch      = 1'd0;

                
            end

            7'h63: begin //B Type
                ImmSel      = 3'd3; 
                RegWrite    = 1'd0;
                ALUSrc      = 1'd0;
                ALUop       = 2'd1;
                MemRead     = 1'd0;
                MemWrite    = 1'd0;
                MemtoReg    = 1'dx;
                Branch      = 1'd1;

            end

            7'h37, 7'h17: begin //U Type
                ImmSel      = 3'd4; 
                RegWrite    = 1'd1;
                ALUSrc      = 1'd1;
                ALUop       = 2'd0;
                MemRead     = 1'd0;
                MemWrite    = 1'd0;
                MemtoReg    = 1'd0;
                Branch      = 1'd0;

            end

            7'h6F: begin //J Type
                ImmSel      = 3'd5; 
                RegWrite    = 1'd1;
                ALUSrc      = 1'dx;
                ALUop       = 2'd0;
                MemRead     = 1'd0;
                MemWrite    = 1'd0;
                MemtoReg    = 1'd0;
                Branch      = 1'd0;

            end

            default: begin 
                ImmSel      = 3'd0;
                RegWrite    = 1'd0;
                ALUSrc      = 1'd0;
                ALUop       = 2'd0;
                MemRead     = 1'd0;
                MemWrite    = 1'd0;
                MemtoReg    = 1'd0;
                Branch      = 1'd0;


            end

        endcase
    
    end

endmodule


module ALU_Sel_Decoder(
    input logic [1:0] ALUop,
    input logic [2:0] funct3,
    input logic       funct7_bit6,

    output logic [3:0] ALU_sel
);


    always @(*) begin
        case(ALUop)
          
            2'd0: ALU_sel = 4'd0;
            2'd1: ALU_sel = 4'd1;
            2'd2, 2'd3: begin
                
                case(funct3)
                    
                    3'b000: begin
                            if(funct7_bit6 == 1'd1 && ALUop == 2'd2) ALU_sel = 4'd1; //Ensure It is R-Type to prevent I type subtraction
                            else ALU_sel = 4'd0;
                            end
                    3'b111: ALU_sel = 4'd2;
                    3'b110: ALU_sel = 4'd3;
                    3'b100: ALU_sel = 4'd4;
                    3'b001: ALU_sel = 4'd5;
                    3'b101: begin   
                            if(funct7_bit6 == 1'd1) ALU_sel = 4'd7;
                            else ALU_sel = 4'd6;
                            end
                    3'b010: ALU_sel = 4'd8;
                    3'b011: ALU_sel = 4'd9;

                    default: ALU_sel = 4'd0;
                endcase

            end
            
            default: ALU_sel = 4'd0;

        endcase

    end

endmodule

Src/cALU_Sel_Decoder_tb.sv
module ALU_Sel_Decoder_tb;

    logic [1:0] ALUop;
    logic [2:0] funct3;
    logic       funct7_bit6;
    logic [3:0] ALU_sel;

    // UUT Instance
    ALU_Sel_Decoder uut (
        .ALUop(ALUop),
        .funct3(funct3),
        .funct7_bit6(funct7_bit6),
        .ALU_sel(ALU_sel)
    );

    initial begin
        $dumpfile("ALU_decode.vcd");
        $dumpvars(0, ALU_Sel_Decoder_tb);

        // Loop through all 64 possible input combinations
        for (int i = 0; i < 64; i++) begin
            
            // Apply inputs by slicing the loop counter
            {ALUop, funct3, funct7_bit6} = i[5:0];
            #1; 

            case (ALUop)
                2'd0: begin // Force ADD path
                    assert(ALU_sel === 4'd0) else $error("Fail ALUop 0: Got %d", ALU_sel);
                end

                2'd1: begin // Force SUB path
                    assert(ALU_sel === 4'd1) else $error("Fail ALUop 1: Got %d", ALU_sel);
                end

                2'd2: begin // R-Type Math Path
                    case (funct3)
                        3'b000:  assert(ALU_sel === (funct7_bit6 ? 4'd1 : 4'd0)) else $error("Fail R-type ADD/SUB");
                        3'b111:  assert(ALU_sel === 4'd2) else $error("Fail R-type AND");
                        3'b110:  assert(ALU_sel === 4'd3) else $error("Fail R-type OR");
                        3'b100:  assert(ALU_sel === 4'd4) else $error("Fail R-type XOR");
                        3'b001:  assert(ALU_sel === 4'd5) else $error("Fail R-type SLL");
                        3'b101:  assert(ALU_sel === (funct7_bit6 ? 4'd7 : 4'd6)) else $error("Fail R-type SRL/SRA");
                        3'b010:  assert(ALU_sel === 4'd8) else $error("Fail R-type SLT");
                        3'b011:  assert(ALU_sel === 4'd9) else $error("Fail R-type SLTU");
                        default: assert(ALU_sel === 4'd0) else $error("Fail R-type Default Latch Protection");
                    endcase
                end

                2'd3: begin // I-Type Math Path
                    case (funct3)
                        3'b000:  assert(ALU_sel === 4'd0) else $error("Fail I-type addi (Bit 30 trap)");
                        3'b111:  assert(ALU_sel === 4'd2) else $error("Fail I-type ANDI");
                        3'b110:  assert(ALU_sel === 4'd3) else $error("Fail I-type ORI");
                        3'b100:  assert(ALU_sel === 4'd4) else $error("Fail I-type XORI");
                        3'b001:  assert(ALU_sel === 4'd5) else $error("Fail I-type SLLI");
                        3'b101:  assert(ALU_sel === (funct7_bit6 ? 4'd7 : 4'd6)) else $error("Fail I-type SRLI/SRAI");
                        3'b010:  assert(ALU_sel === 4'd8) else $error("Fail I-type SLTI");
                        3'b011:  assert(ALU_sel === 4'd9) else $error("Fail I-type SLTIU");
                        default: assert(ALU_sel === 4'd0) else $error("Fail I-type Default Latch Protection");
                    endcase
                end
            endcase
        end

        $display("ALU Decoder Test Complete. If no errors were printed, it works");
        $finish;
    end
endmodule

Src/ALU_decode.vcd
$date
	Sun Jun 07 20:39:23 2026
$end
$version
	Icarus Verilog
$end
$timescale
	1s
$end
$scope module ALU_Sel_Decoder_tb $end
$var wire 4 ! ALU_sel [3:0] $end
$var reg 2 " ALUop [1:0] $end
$var reg 3 # funct3 [2:0] $end
$var reg 1 $ funct7_bit6 $end
$scope module uut $end
$var wire 2 % ALUop [1:0] $end
$var wire 3 & funct3 [2:0] $end
$var wire 1 $ funct7_bit6 $end
$var reg 4 ' ALU_sel [3:0] $end
$upscope $end
$scope begin $ivl_for_loop0 $end
$var integer 32 ( i [31:0] $end
$upscope $end
$upscope $end
$enddefinitions $end
$comment Show the parameter values. $end
$dumpall
$end
#0
$dumpvars
b0 (
b0 '
b0 &
b0 %
0$
b0 #
b0 "
b0 !
$end
#1
1$
b1 (
#2
b1 #
b1 &
0$
b10 (
#3
1$
b11 (
#4
b10 #
b10 &
0$
b100 (
#5
1$
b101 (
#6
b11 #
b11 &
0$
b110 (
#7
1$
b111 (
#8
b100 #
b100 &
0$
b1000 (
#9
1$
b1001 (
#10
b101 #
b101 &
0$
b1010 (
#11
1$
b1011 (
#12
b110 #
b110 &
0$
b1100 (
#13
1$
b1101 (
#14
b111 #
b111 &
0$
b1110 (
#15
1$
b1111 (
#16
b1 !
b1 '
b1 "
b1 %
b0 #
b0 &
0$
b10000 (
#17
1$
b10001 (
#18
b1 #
b1 &
0$
b10010 (
#19
1$
b10011 (
#20
b10 #
b10 &
0$
b10100 (
#21
1$
b10101 (
#22
b11 #
b11 &
0$
b10110 (
#23
1$
b10111 (
#24
b100 #
b100 &
0$
b11000 (
#25
1$
b11001 (
#26
b101 #
b101 &
0$
b11010 (
#27
1$
b11011 (
#28
b110 #
b110 &
0$
b11100 (
#29
1$
b11101 (
#30
b111 #
b111 &
0$
b11110 (
#31
1$
b11111 (
#32
b0 !
b0 '
b10 "
b10 %
b0 #
b0 &
0$
b100000 (
#33
b1 !
b1 '
1$
b100001 (
#34
b101 !
b101 '
b1 #
b1 &
0$
b100010 (
#35
1$
b100011 (
#36
b1000 !
b1000 '
b10 #
b10 &
0$
b100100 (
#37
1$
b100101 (
#38
b1001 !
b1001 '
b11 #
b11 &
0$
b100110 (
#39
1$
b100111 (
#40
b100 !
b100 '
b100 #
b100 &
0$
b101000 (
#41
1$
b101001 (
#42
b110 !
b110 '
b101 #
b101 &
0$
b101010 (
#43
b111 !
b111 '
1$
b101011 (
#44
b11 !
b11 '
b110 #
b110 &
0$
b101100 (
#45
1$
b101101 (
#46
b10 !
b10 '
b111 #
b111 &
0$
b101110 (
#47
1$
b101111 (
#48
b0 !
b0 '
b11 "
b11 %
b0 #
b0 &
0$
b110000 (
#49
1$
b110001 (
#50
b101 !
b101 '
b1 #
b1 &
0$
b110010 (
#51
1$
b110011 (
#52
b1000 !
b1000 '
b10 #
b10 &
0$
b110100 (
#53
1$
b110101 (
#54
b1001 !
b1001 '
b11 #
b11 &
0$
b110110 (
#55
1$
b110111 (
#56
b100 !
b100 '
b100 #
b100 &
0$
b111000 (
#57
1$
b111001 (
#58
b110 !
b110 '
b101 #
b101 &
0$
b111010 (
#59
b111 !
b111 '
1$
b111011 (
#60
b11 !
b11 '
b110 #
b110 &
0$
b111100 (
#61
1$
b111101 (
#62
b10 !
b10 '
b111 #
b111 &
0$
b111110 (
#63
1$
b111111 (
#64
b1000000 (
