Src/PC.sv
module PC_reg(
    input  logic clk, rst_n, branch_taken,
    input  logic [31:0] branch_target,
    output logic [31:0] pc_out
);

always_ff @(posedge clk or negedge rst_n) begin

    if (!rst_n) begin
        pc_out <= 32'h0;
    end else begin
        if (branch_taken) begin
            pc_out <= branch_target;

        end else begin
            pc_out <= pc_out + 32'd4;

        end
        
    end


end

endmodule

Src/PC_tb.sv
module pc_tb;

    logic clk;
    logic rst_n;
    logic branch_taken;
    logic [31:0] branch_target;
    logic [31:0] pc_out;

    parameter CLK_PERIOD = 10;

    //Instantiate the PC module
    PC_reg regTest(
        .clk(clk),
        .rst_n(rst_n),
        .branch_taken(branch_taken),
        .branch_target(branch_target),
        .pc_out(pc_out)
    );  

    //Clock generation separate from stimulus
    initial clk = 0;
    always #(CLK_PERIOD/2) clk = ~clk;

    initial begin

        $dumpfile("pc.vcd");
        $dumpvars(0, pc_tb);

        // initialize in reset state
        rst_n = 0;
        branch_taken = 0;
        branch_target = 32'h0;



        // Test 1: reset
        @(posedge clk); #1;
        if(pc_out == 0) 
            $display("branch_taken = 0: Success: pc_out = 0");
        else
            $error("Failure: Expected 0, got %d", pc_out);

        rst_n = 1;
        
        // Test 2: branch_taken = 0
        for(int i = 1; i<8; i++) begin
            @(posedge clk); #1;
            
            if(pc_out == 32'(i * 4)) 
                $display("branch_taken = 0: Success: pc_out = %d", (4*i));
            else 
                $error("Failure: Expected %d, got %d", (4*i), pc_out);
        end


        branch_taken = 1;

        // Test3: branch_taken = 1
        for (int i=0; i<31; i++) begin
        branch_target = i;

        @(posedge clk); #1;
        
        $display("Loop iteration: %d", i);
        if(pc_out == branch_target)
            $display("branch_taken = 0: Success: pc_out = %d", branch_target);
        else
            $error("Failure: Expected %d, got %d", branch_target, pc_out);

        end

        $finish;
    end

endmodule

Src/pc.vcd
$date
	Sat May 09 17:03:05 2026
$end
$version
	Icarus Verilog
$end
$timescale
	1s
$end
$scope module pc_tb $end
$var wire 32 ! pc_out [31:0] $end
$var parameter 32 " CLK_PERIOD $end
$var reg 1 # branch_taken $end
$var reg 32 $ branch_target [31:0] $end
$var reg 1 % clk $end
$var reg 1 & rst_n $end
$scope module regTest $end
$var wire 1 # branch_taken $end
$var wire 32 ' branch_target [31:0] $end
$var wire 1 % clk $end
$var wire 1 & rst_n $end
$var reg 32 ( pc_out [31:0] $end
$upscope $end
$scope begin $ivl_for_loop0 $end
$var integer 32 ) i [31:0] $end
$upscope $end
$scope begin $ivl_for_loop1 $end
$var integer 32 * i [31:0] $end
$upscope $end
$upscope $end
$enddefinitions $end
$comment Show the parameter values. $end
$dumpall
b1010 "
$end
#0
$dumpvars
b0 *
b0 )
b0 (
b0 '
0&
0%
b0 $
0#
b0 !
$end
#5
1%
#6
b1 )
1&
#10
0%
#15
b100 !
b100 (
1%
#16
b10 )
#20
0%
#25
b1000 !
b1000 (
1%
#26
b11 )
#30
0%
#35
b1100 !
b1100 (
1%
#36
b100 )
#40
0%
#45
b10000 !
b10000 (
1%
#46
b101 )
#50
0%
#55
b10100 !
b10100 (
1%
#56
b110 )
#60
0%
#65
b11000 !
b11000 (
1%
#66
b111 )
#70
0%
#75
b11100 !
b11100 (
1%
#76
1#
b1000 )
#80
0%
#85
b0 !
b0 (
1%
#86
b1 $
b1 '
b1 *
#90
0%
#95
b1 !
b1 (
1%
#96
b10 $
b10 '
b10 *
#100
0%
#105
b10 !
b10 (
1%
#106
b11 $
b11 '
b11 *
#110
0%
#115
b11 !
b11 (
1%
#116
b100 $
b100 '
b100 *
#120
0%
#125
b100 !
b100 (
1%
#126
b101 $
b101 '
b101 *
#130
0%
#135
b101 !
b101 (
1%
#136
b110 $
b110 '
b110 *
#140
0%
#145
b110 !
b110 (
1%
#146
b111 $
b111 '
b111 *
#150
0%
#155
b111 !
b111 (
1%
#156
b1000 $
b1000 '
b1000 *
#160
0%
#165
b1000 !
b1000 (
1%
#166
b1001 $
b1001 '
b1001 *
#170
0%
#175
b1001 !
b1001 (
1%
#176
b1010 $
b1010 '
b1010 *
#180
0%
#185
b1010 !
b1010 (
1%
#186
b1011 $
b1011 '
b1011 *
#190
0%
#195
b1011 !
b1011 (
1%
#196
b1100 $
b1100 '
b1100 *
#200
0%
#205
b1100 !
b1100 (
1%
#206
b1101 $
b1101 '
b1101 *
#210
0%
#215
b1101 !
b1101 (
1%
#216
b1110 $
b1110 '
b1110 *
#220
0%
#225
b1110 !
b1110 (
1%
#226
b1111 $
b1111 '
b1111 *
#230
0%
#235
b1111 !
b1111 (
1%
#236
b10000 $
b10000 '
b10000 *
#240
0%
#245
b10000 !
b10000 (
1%
#246
b10001 $
b10001 '
b10001 *
#250
0%
#255
b10001 !
b10001 (
1%
#256
b10010 $
b10010 '
b10010 *
#260
0%
#265
b10010 !
b10010 (
1%
#266
b10011 $
b10011 '
b10011 *
#270
0%
#275
b10011 !
b10011 (
1%
#276
b10100 $
b10100 '
b10100 *
#280
0%
#285
b10100 !
b10100 (
1%
#286
b10101 $
b10101 '
b10101 *
#290
0%
#295
b10101 !
b10101 (
1%
#296
b10110 $
b10110 '
b10110 *
#300
0%
#305
b10110 !
b10110 (
1%
#306
b10111 $
b10111 '
b10111 *
#310
0%
#315
b10111 !
b10111 (
1%
#316
b11000 $
b11000 '
b11000 *
#320
0%
#325
b11000 !
b11000 (
1%
#326
b11001 $
b11001 '
b11001 *
#330
0%
#335
b11001 !
b11001 (
1%
#336
b11010 $
b11010 '
b11010 *
#340
0%
#345
b11010 !
b11010 (
1%
#346
b11011 $
b11011 '
b11011 *
#350
0%
#355
b11011 !
b11011 (
1%
#356
b11100 $
b11100 '
b11100 *
#360
0%
#365
b11100 !
b11100 (
1%
#366
b11101 $
b11101 '
b11101 *
#370
0%
#375
b11101 !
b11101 (
1%
#376
b11110 $
b11110 '
b11110 *
#380
0%
#385
b11110 !
b11110 (
1%
#386
b11111 *
