Src/regFile.sv
module regFile (
    input logic clk,
    input logic [4:0] rs1, //reading registers
    input logic [4:0] rs2,
    input logic [4:0] rw, //register to write to
    input logic [31:0] ww, //what you are writing to the register
    input logic we, // enable writing
    
    output logic [31:0] rd1, // output what the registers read
    output logic [31:0] rd2
);
        
    logic [31:0] mainReg [0:31];

    initial begin
        for(int i = 0; i<32; i++) begin
             mainReg[i] = 32'h0;
        end
    end


    assign rd1 = mainReg[rs1];
    assign rd2 = mainReg[rs2];

    always_ff @(posedge clk) begin
    
        if(we && (rw != 5'b0)) mainReg[rw] <= ww; 

    end


endmodule

Src/regFile_tb.sv
    module regFile_tb;

        parameter CLK_PERIOD = 10;

        logic clk;
        logic [4:0] rs1;
        logic [4:0] rs2;
        logic [4:0] rw;
        logic [31:0] ww;
        logic we;

        logic [31:0] rd1;
        logic [31:0] rd2;


        regFile testReg (

            .clk(clk),
            .rs1(rs1),
            .rs2(rs2),
            .rw(rw),
            .ww(ww),
            .we(we),

            .rd1(rd1),
            .rd2(rd2)
        );

        initial clk = 0;
        always #(CLK_PERIOD/2) clk = ~clk;

        initial begin
            
            $dumpfile("regfile.vcd");
            $dumpvars(0, regFile_tb);

            // Test 1: writing when enabled to
            we = 1;
            rw = 5'd3;
            rs1 = 5'd3;
            ww = 32'd4;
            @(posedge clk); #1;
            if(rd1 == ww)
                $display("Success: rd1 = %d", rd1);
            else
                $error("Failure: Expected %d, got %d", ww, rd1);  

            rw = 5'd4;
            rs2 = 5'd4;
            ww = 32'd5;
            @(posedge clk); #1;
            if(rd2 == ww)
                $display("Success: rd1 = %d", rd1);
            else
                $error("Failure: Expected %d, got %d", ww, rd2);  

            
            // Test 2: writing when not enabled to
            we = 0;
            rw = 5'd3;
            rs1 = 5'd3;
            ww = 32'd9;
            @(posedge clk); #1;
            if(rd1 == 32'd4)
                $display("Success: rd1 = %d", rd1);
            else
                $error("Failure: Expected %d, got %d", 32'd4, rd1);  

            rw = 5'd4;
            rs2 = 5'd4;
            ww = 32'd9;
            @(posedge clk); #1;
            if(rd2 == 32'd5)
                $display("Success: rd1 = %d", rd2);
            else
                $error("Failure: Expected %d, got %d", 32'd5, rd1);


            // Test 3: writing to register 0
            we = 1;
            rw = 5'd0;
            rs1 = 5'd0;
            ww = 32'd9;
            @(posedge clk); #1;
            if(rd1 == 32'h0)
                $display("Success: rd1 = %d", rd1);
            else
                $error("Failure: Expected %d, got %d", 32'h0, rd1); 


            // Test 4: checking that both rs work at the same time
            we = 0;
            rs1 = 5'd3;
            rs2 = 5'd4;
            @(posedge clk); #1;
            if(rd1 == 32'd4 && rd2 == 32'd5)
                $display("Success: rd1 = %d, rd2 = %d", rd1, rd2);
            else
                $error("Failure: rd1: Expected %d, got %d, rd2: Expected %d, got %d", 32'd4, rd1, 32'd5, rd2);

            $finish;
        end


    endmodule

Src/regfile.vcd
$date
	Sat May 09 22:37:48 2026
$end
$version
	Icarus Verilog
$end
$timescale
	1s
$end
$scope module regFile_tb $end
$var wire 32 ! rd2 [31:0] $end
$var wire 32 " rd1 [31:0] $end
$var parameter 32 # CLK_PERIOD $end
$var reg 1 $ clk $end
$var reg 5 % rs1 [4:0] $end
$var reg 5 & rs2 [4:0] $end
$var reg 5 ' rw [4:0] $end
$var reg 1 ( we $end
$var reg 32 ) ww [31:0] $end
$scope module testReg $end
$var wire 1 $ clk $end
$var wire 32 * rd1 [31:0] $end
$var wire 32 + rd2 [31:0] $end
$var wire 5 , rs1 [4:0] $end
$var wire 5 - rs2 [4:0] $end
$var wire 5 . rw [4:0] $end
$var wire 1 ( we $end
$var wire 32 / ww [31:0] $end
$scope begin $ivl_for_loop0 $end
$var integer 32 0 i [31:0] $end
$upscope $end
$upscope $end
$upscope $end
$enddefinitions $end
$comment Show the parameter values. $end
$dumpall
b1010 #
$end
#0
$dumpvars
b100000 0
b100 /
b11 .
bx -
b11 ,
bx +
b0 *
b100 )
1(
b11 '
bx &
b11 %
0$
b0 "
bx !
$end
#5
b100 "
b100 *
1$
#6
b101 )
b101 /
b0 !
b0 +
b100 &
b100 -
b100 '
b100 .
#10
0$
#15
b101 !
b101 +
1$
#16
b1001 )
b1001 /
b11 '
b11 .
0(
#20
0$
#25
1$
#26
b100 '
b100 .
#30
0$
#35
1$
#36
b0 "
b0 *
b0 %
b0 ,
b0 '
b0 .
1(
#40
0$
#45
1$
#46
b100 "
b100 *
b11 %
b11 ,
0(
